{
    "meta": {
        "api_name": "get_script_languages",
        "stability": "stable",
        "visibility": "public",
        "main_component": "get_script_languages",
        "url": "https://www.elastic.co/guide/en/elasticsearch/reference/master/modules-scripting.html",
        "elastic_url": "https://www.elastic.co/get_script_languages.html",
        "treat_json_as_key_value": false,
        "title": "Returns available script types, languages and contexts",
        "paths": [
            {
                "path": "/_script_language",
                "methods": [
                    "GET"
                ]
            }
        ],
        "parameter_types": {},
        "type": "api_spec"
    },
    "doc": {
        "documentation": {
            "url": "https://www.elastic.co/guide/en/elasticsearch/reference/master/modules-scripting.html",
            "description": "Returns available script types, languages and contexts"
        },
        "stability": "stable",
        "visibility": "public",
        "headers": {
            "accept": [
                "application/json"
            ]
        },
        "url": {
            "paths": [
                {
                    "path": "/_script_language",
                    "methods": [
                        "GET"
                    ]
                }
            ]
        },
        "params": {}
    }
}