{
    "meta": {
        "timestamp": "2024-11-01T03:07:11.499271",
        "api_name": "ml.reset_job",
        "stability": "stable",
        "visibility": "public",
        "main_component": "ml",
        "url": "https://www.elastic.co/guide/en/elasticsearch/reference/current/ml-reset-job.html",
        "elastic_url": "https://www.elastic.co/ml/reset_job.html",
        "treat_json_as_key_value": false,
        "title": "Resets an existing anomaly detection job.",
        "paths": [
            {
                "path": "/_ml/anomaly_detectors/{job_id}/_reset",
                "methods": [
                    "POST"
                ],
                "parts": {
                    "job_id": {
                        "type": "string",
                        "description": "The ID of the job to reset"
                    }
                }
            }
        ],
        "parameter_types": {
            "wait_for_completion": "boolean",
            "delete_user_annotations": "boolean"
        },
        "type": "api_spec"
    },
    "doc": {
        "documentation": {
            "url": "https://www.elastic.co/guide/en/elasticsearch/reference/current/ml-reset-job.html",
            "description": "Resets an existing anomaly detection job."
        },
        "stability": "stable",
        "visibility": "public",
        "headers": {
            "accept": [
                "application/json"
            ]
        },
        "url": {
            "paths": [
                {
                    "path": "/_ml/anomaly_detectors/{job_id}/_reset",
                    "methods": [
                        "POST"
                    ],
                    "parts": {
                        "job_id": {
                            "type": "string",
                            "description": "The ID of the job to reset"
                        }
                    }
                }
            ]
        },
        "params": {
            "wait_for_completion": {
                "type": "boolean",
                "description": "Should this request wait until the operation has completed before returning",
                "default": true
            },
            "delete_user_annotations": {
                "type": "boolean",
                "description": "Should annotations added by the user be deleted",
                "default": false
            }
        }
    }
}