{
    "meta": {
        "api_name": "synonyms.get_synonyms_sets",
        "stability": "stable",
        "visibility": "public",
        "main_component": "synonyms",
        "url": "https://www.elastic.co/guide/en/elasticsearch/reference/master/list-synonyms-sets.html",
        "elastic_url": "https://www.elastic.co/synonyms/get_synonyms_sets.html",
        "treat_json_as_key_value": false,
        "title": "Retrieves a summary of all defined synonym sets",
        "paths": [
            {
                "path": "/_synonyms",
                "methods": [
                    "GET"
                ]
            }
        ],
        "parameter_types": {
            "from": "int",
            "size": "int"
        },
        "type": "api_spec"
    },
    "doc": {
        "documentation": {
            "url": "https://www.elastic.co/guide/en/elasticsearch/reference/master/list-synonyms-sets.html",
            "description": "Retrieves a summary of all defined synonym sets"
        },
        "stability": "stable",
        "visibility": "public",
        "headers": {
            "accept": [
                "application/json"
            ]
        },
        "url": {
            "paths": [
                {
                    "path": "/_synonyms",
                    "methods": [
                        "GET"
                    ]
                }
            ]
        },
        "params": {
            "from": {
                "type": "int",
                "description": "Starting offset",
                "default": 0
            },
            "size": {
                "type": "int",
                "description": "specifies a max number of results to get",
                "default": 10
            }
        }
    }
}